{
  "id": "aws2",
  "name": "aws2",
  "version": "2025.9.11",
  "customizations": {
    "manifest": {
      "dependencies": [
        {
          "name": "cli",
          "version": "2.30.0",
          "hint": "tags/v?[0-9]+\\.[0-9]+(\\.[0-9]+)?",
          "repository": "github.com/aws/aws-cli",
          "artifacts": [
            {
              "architecture": "amd64",
              "url": "https://awscli.amazonaws.com/awscli-exe-linux-x86_64-${VERSION}.zip",
              "checksum": "ad1314f3c1c99d4de006d10cd579061afe92f70adfe94012413ea3df8b7c219a"
            },
            {
              "architecture": "arm64",
              "url": "https://awscli.amazonaws.com/awscli-exe-linux-aarch64-${VERSION}.zip",
              "checksum": "ad017987d0bae202c3cfdfae8483fa17107d20026f175d25b0947a5221c4fb36"
            }
          ]
        }
      ]
    }
  }
}
